README.md
license.txt
setup.py
VideoPro10.egg-info/PKG-INFO
VideoPro10.egg-info/SOURCES.txt
VideoPro10.egg-info/dependency_links.txt
VideoPro10.egg-info/top_level.txt
pro_video_ferramentas/__init__.py
pro_video_ferramentas/camera.py
pro_video_ferramentas/video.py