Metadata-Version: 2.1
Name: VideoPro10
Version: 1.0
Summary: Este pacote irá fornecer ferramentas de processamento de video
Author: Paulo Ribas
Author-email: paulo-ribas@live.com
Keywords: camera,video,processamento
License-File: license.txt
